{"nodes": [{"id": "c_users_s_desktop_fpga_spectrumanalyzer_docs_synthesis_schematic_md", "label": "synthesis_schematic.md", "file_type": "document", "source_file": "C:\\Users\\S\\Desktop\\FPGA\\SpectrumAnalyzer\\docs\\synthesis_schematic.md", "source_location": "L1"}, {"id": "docs_synthesis_schematic_\u7efc\u5408\u7535\u8def\u56fe\u8bf4\u660e", "label": "\u7efc\u5408\u7535\u8def\u56fe\u8bf4\u660e", "file_type": "document", "source_file": "C:\\Users\\S\\Desktop\\FPGA\\SpectrumAnalyzer\\docs\\synthesis_schematic.md", "source_location": "L1"}, {"id": "docs_synthesis_schematic_1_\u9a8c\u6536\u76ee\u6807", "label": "1. \u9a8c\u6536\u76ee\u6807", "file_type": "document", "source_file": "C:\\Users\\S\\Desktop\\FPGA\\SpectrumAnalyzer\\docs\\synthesis_schematic.md", "source_location": "L3"}, {"id": "docs_synthesis_schematic_2_\u751f\u6210\u7efc\u5408\u7ed3\u679c", "label": "2. \u751f\u6210\u7efc\u5408\u7ed3\u679c", "file_type": "document", "source_file": "C:\\Users\\S\\Desktop\\FPGA\\SpectrumAnalyzer\\docs\\synthesis_schematic.md", "source_location": "L7"}, {"id": "docs_synthesis_schematic_3_vivado_gui_\u67e5\u770b\u6b65\u9aa4", "label": "3. Vivado GUI \u67e5\u770b\u6b65\u9aa4", "file_type": "document", "source_file": "C:\\Users\\S\\Desktop\\FPGA\\SpectrumAnalyzer\\docs\\synthesis_schematic.md", "source_location": "L24"}, {"id": "docs_synthesis_schematic_4_\u7b54\u8fa9\u8bb2\u89e3\u53e3\u5f84", "label": "4. \u7b54\u8fa9\u8bb2\u89e3\u53e3\u5f84", "file_type": "document", "source_file": "C:\\Users\\S\\Desktop\\FPGA\\SpectrumAnalyzer\\docs\\synthesis_schematic.md", "source_location": "L46"}, {"id": "docs_synthesis_schematic_5_ip_\u4e0e_rtl_\u6807\u6ce8", "label": "5. IP \u4e0e RTL \u6807\u6ce8", "file_type": "document", "source_file": "C:\\Users\\S\\Desktop\\FPGA\\SpectrumAnalyzer\\docs\\synthesis_schematic.md", "source_location": "L58"}], "edges": [{"source": "c_users_s_desktop_fpga_spectrumanalyzer_docs_synthesis_schematic_md", "target": "docs_synthesis_schematic_\u7efc\u5408\u7535\u8def\u56fe\u8bf4\u660e", "relation": "contains", "confidence": "EXTRACTED", "source_file": "C:\\Users\\S\\Desktop\\FPGA\\SpectrumAnalyzer\\docs\\synthesis_schematic.md", "source_location": "L1", "weight": 1.0}, {"source": "docs_synthesis_schematic_\u7efc\u5408\u7535\u8def\u56fe\u8bf4\u660e", "target": "docs_synthesis_schematic_1_\u9a8c\u6536\u76ee\u6807", "relation": "contains", "confidence": "EXTRACTED", "source_file": "C:\\Users\\S\\Desktop\\FPGA\\SpectrumAnalyzer\\docs\\synthesis_schematic.md", "source_location": "L3", "weight": 1.0}, {"source": "docs_synthesis_schematic_\u7efc\u5408\u7535\u8def\u56fe\u8bf4\u660e", "target": "docs_synthesis_schematic_2_\u751f\u6210\u7efc\u5408\u7ed3\u679c", "relation": "contains", "confidence": "EXTRACTED", "source_file": "C:\\Users\\S\\Desktop\\FPGA\\SpectrumAnalyzer\\docs\\synthesis_schematic.md", "source_location": "L7", "weight": 1.0}, {"source": "docs_synthesis_schematic_\u7efc\u5408\u7535\u8def\u56fe\u8bf4\u660e", "target": "docs_synthesis_schematic_3_vivado_gui_\u67e5\u770b\u6b65\u9aa4", "relation": "contains", "confidence": "EXTRACTED", "source_file": "C:\\Users\\S\\Desktop\\FPGA\\SpectrumAnalyzer\\docs\\synthesis_schematic.md", "source_location": "L24", "weight": 1.0}, {"source": "docs_synthesis_schematic_\u7efc\u5408\u7535\u8def\u56fe\u8bf4\u660e", "target": "docs_synthesis_schematic_4_\u7b54\u8fa9\u8bb2\u89e3\u53e3\u5f84", "relation": "contains", "confidence": "EXTRACTED", "source_file": "C:\\Users\\S\\Desktop\\FPGA\\SpectrumAnalyzer\\docs\\synthesis_schematic.md", "source_location": "L46", "weight": 1.0}, {"source": "docs_synthesis_schematic_\u7efc\u5408\u7535\u8def\u56fe\u8bf4\u660e", "target": "docs_synthesis_schematic_5_ip_\u4e0e_rtl_\u6807\u6ce8", "relation": "contains", "confidence": "EXTRACTED", "source_file": "C:\\Users\\S\\Desktop\\FPGA\\SpectrumAnalyzer\\docs\\synthesis_schematic.md", "source_location": "L58", "weight": 1.0}], "input_tokens": 0, "output_tokens": 0}